bitnet_v3/__init__.py
bitnet_v3/core/__init__.py
bitnet_v3/core/hadamard.py
bitnet_v3/core/quantization.py
bitnet_v3/core/straight_through.py
bitnet_v3/examples/__init__.py
bitnet_v3/examples/basic_usage.py
bitnet_v3/models/__init__.py
bitnet_v3/models/bitnet_v3.py
bitnet_v3/models/transformer.py
bitnet_v3/modules/__init__.py
bitnet_v3/modules/aht_lp.py
bitnet_v3/modules/bitlinear.py
bitnet_v3/modules/dr_qap.py
bitnet_v3/modules/este_m.py
bitnet_v3/modules/gakd.py
bitnet_v3/modules/mpq.py
bitnet_v3-1.0.1.dist-info/licenses/LICENSE
bitnet_v3-1.0.1.dist-info/METADATA
bitnet_v3-1.0.1.dist-info/WHEEL
bitnet_v3-1.0.1.dist-info/entry_points.txt
bitnet_v3-1.0.1.dist-info/top_level.txt
bitnet_v3-1.0.1.dist-info/RECORD
