Metadata-Version: 2.4
Name: bitnet-v3
Version: 1.0.1
Summary: BitNet v3: Ultra-Low Quality Loss 1-bit LLMs Through Multi-Stage Progressive Quantization and Adaptive Hadamard Transform
Home-page: https://github.com/ProCreations-Official/bitnet-v3
Author: ProCreations
License: MIT
Project-URL: Homepage, https://github.com/ProCreations-Official/bitnet-v3
Project-URL: Documentation, https://github.com/ProCreations-Official/bitnet-v3/blob/main/README.md
Project-URL: Repository, https://github.com/ProCreations-Official/bitnet-v3
Project-URL: Bug Tracker, https://github.com/ProCreations-Official/bitnet-v3/issues
Project-URL: Changelog, https://github.com/ProCreations-Official/bitnet-v3/blob/main/CHANGELOG.md
Keywords: bitnet,quantization,1-bit,llm,transformer,hadamard,knowledge-distillation,neural-networks,deep-learning,pytorch
Classifier: Development Status :: 4 - Beta
Classifier: Intended Audience :: Developers
Classifier: Intended Audience :: Science/Research
Classifier: License :: OSI Approved :: MIT License
Classifier: Operating System :: OS Independent
Classifier: Programming Language :: Python :: 3
Classifier: Programming Language :: Python :: 3.8
Classifier: Programming Language :: Python :: 3.9
Classifier: Programming Language :: Python :: 3.10
Classifier: Programming Language :: Python :: 3.11
Classifier: Topic :: Scientific/Engineering :: Artificial Intelligence
Classifier: Topic :: Software Development :: Libraries :: Python Modules
Requires-Python: >=3.8
License-File: LICENSE
Requires-Dist: torch>=2.0.0
Requires-Dist: torchvision>=0.15.0
Requires-Dist: numpy>=1.21.0
Requires-Dist: scipy>=1.7.0
Requires-Dist: einops>=0.6.0
Requires-Dist: accelerate>=0.20.0
Requires-Dist: transformers>=4.30.0
Requires-Dist: datasets>=2.0.0
Requires-Dist: tokenizers>=0.13.0
Requires-Dist: tqdm>=4.60.0
Requires-Dist: pyyaml>=6.0
Requires-Dist: omegaconf>=2.3.0
Requires-Dist: wandb>=0.15.0
Requires-Dist: tensorboard>=2.13.0
Requires-Dist: bitsandbytes>=0.41.0
Requires-Dist: safetensors>=0.3.0
Provides-Extra: dev
Requires-Dist: pytest>=6.0; extra == "dev"
Requires-Dist: pytest-cov>=2.0; extra == "dev"
Requires-Dist: black>=21.0; extra == "dev"
Requires-Dist: isort>=5.0; extra == "dev"
Requires-Dist: flake8>=3.8; extra == "dev"
Requires-Dist: mypy>=0.800; extra == "dev"
Requires-Dist: pre-commit>=2.0; extra == "dev"
Provides-Extra: docs
Requires-Dist: sphinx>=4.0; extra == "docs"
Requires-Dist: sphinx-rtd-theme>=1.0; extra == "docs"
Requires-Dist: myst-parser>=0.15; extra == "docs"
Provides-Extra: examples
Requires-Dist: matplotlib>=3.3; extra == "examples"
Requires-Dist: seaborn>=0.11; extra == "examples"
Requires-Dist: tqdm>=4.60; extra == "examples"
Requires-Dist: datasets>=1.8; extra == "examples"
Requires-Dist: transformers>=4.20; extra == "examples"
Provides-Extra: all
Requires-Dist: flash-attn>=2.0.0; extra == "all"
Requires-Dist: xformers>=0.0.20; extra == "all"
Dynamic: home-page
Dynamic: license-file
Dynamic: requires-python
